hubitatmaker/__init__.py
hubitatmaker/const.py
hubitatmaker/error.py
hubitatmaker/hub.py
hubitatmaker/py.typed
hubitatmaker/server.py
hubitatmaker/tests/__init__.py
hubitatmaker/tests/device_details.json
hubitatmaker/tests/devices.json
hubitatmaker/tests/events.json
hubitatmaker/tests/hsm.json
hubitatmaker/tests/hub_edit.html
hubitatmaker/tests/modes.json
hubitatmaker/tests/test_hub.py
hubitatmaker/tests/test_types.py
hubitatmaker/types.py
hubitatmaker-0.6.1.dist-info/WHEEL
hubitatmaker-0.6.1.dist-info/METADATA
hubitatmaker-0.6.1.dist-info/license_files/LICENSE
hubitatmaker-0.6.1.dist-info/RECORD
