Metadata-Version: 2.1
Name: hubitatmaker
Version: 0.6.1
Summary: A library for interfacing with Hubitat via its Maker API
License: MIT
Keywords: hubitat
Author-email: Jason Cheatham <jason@jasoncheatham.com>
Requires-Python: >=3.8,<4.0
Classifier: Development Status :: 3 - Alpha
Classifier: Intended Audience :: Developers
Classifier: License :: OSI Approved :: MIT License
Classifier: Operating System :: OS Independent
Classifier: Programming Language :: Python :: 3.8
Classifier: Topic :: Home Automation
Classifier: Typing :: Typed
Requires-Dist: aiohttp<4.0.0,>=3.6.2
Requires-Dist: getmac<1.0.0,>=0.8.2
Project-URL: homepage, https://github.com/jason0x43/hubitatmaker
